quanturf_test/__init__.py
quanturf_test/__main__.py
quanturf_test/jupyter_notebook_config.py
quanturf_test/quanturf.ipynb
quanturf_test-7.5.data/data/version.py
quanturf_test-7.5.dist-info/METADATA
quanturf_test-7.5.dist-info/WHEEL
quanturf_test-7.5.dist-info/entry_points.txt
quanturf_test-7.5.dist-info/top_level.txt
quanturf_test-7.5.dist-info/RECORD
